{
    "available_space": true,
    "content": [
        {
            "id": "2pqSKlI3QuU",
            "name": "Claptone - Dear Life ft. Jaw (FULL EP) \uff5c TSTLM [2pqSKlI3QuU].mp4",
            "path": "/home/alanmatzumiya/Videos/container/o4/videos/Claptone - Dear Life ft. Jaw (FULL EP) \uff5c TSTLM [2pqSKlI3QuU].mp4",
            "size": 26.710987,
            "url": "https://github.com/circuitalmynds/music_o4/blob/main/videos/Claptone - Dear Life ft. Jaw (FULL EP) \uff5c TSTLM [2pqSKlI3QuU].mp4?raw=true"
        },
        {
            "id": "-iVR7WLsvAg",
            "name": "Street Life - The Crusaders '1979 [-iVR7WLsvAg].mp4",
            "path": "/home/alanmatzumiya/Videos/container/o4/videos/Street Life - The Crusaders '1979 [-iVR7WLsvAg].mp4",
            "size": 5.839814,
            "url": "https://github.com/circuitalmynds/music_o4/blob/main/videos/Street Life - The Crusaders '1979 [-iVR7WLsvAg].mp4?raw=true"
        },
        {
            "id": "e6iji6p2YCQ",
            "name": "Summer Daze [e6iji6p2YCQ].mp4",
            "path": "/home/alanmatzumiya/Videos/container/o4/videos/Summer Daze [e6iji6p2YCQ].mp4",
            "size": 7.625067,
            "url": "https://github.com/circuitalmynds/music_o4/blob/main/videos/Summer Daze [e6iji6p2YCQ].mp4?raw=true"
        },
        {
            "id": "_wQ9mlQ2fVU",
            "name": "Piano Concerto in D Minor (1812) \uff1a I. Allegro molto agitato [_wQ9mlQ2fVU].mp4",
            "path": "/home/alanmatzumiya/Videos/container/o4/videos/Piano Concerto in D Minor (1812) \uff1a I. Allegro molto agitato [_wQ9mlQ2fVU].mp4",
            "size": 41.401354,
            "url": "https://github.com/circuitalmynds/music_o4/blob/main/videos/Piano Concerto in D Minor (1812) \uff1a I. Allegro molto agitato [_wQ9mlQ2fVU].mp4?raw=true"
        },
        {
            "id": "nwf3XglwAwY",
            "name": "Nina Hagen - Go ahead (video) [nwf3XglwAwY].mp4",
            "path": "/home/alanmatzumiya/Videos/container/o4/videos/Nina Hagen - Go ahead (video) [nwf3XglwAwY].mp4",
            "size": 16.899229,
            "url": "https://github.com/circuitalmynds/music_o4/blob/main/videos/Nina Hagen - Go ahead (video) [nwf3XglwAwY].mp4?raw=true"
        },
        {
            "id": "yMZLaEaiwSs",
            "name": "Monbar, Op. 30, \uff02The Filibusters\uff02\uff1a Overture [yMZLaEaiwSs].mp4",
            "path": "/home/alanmatzumiya/Videos/container/o4/videos/Monbar, Op. 30, \uff02The Filibusters\uff02\uff1a Overture [yMZLaEaiwSs].mp4",
            "size": 38.139879,
            "url": "https://github.com/circuitalmynds/music_o4/blob/main/videos/Monbar, Op. 30, \uff02The Filibusters\uff02\uff1a Overture [yMZLaEaiwSs].mp4?raw=true"
        },
        {
            "id": "2QxzWdMjI4A",
            "name": "Oscar Aleman. The Platinum Collection. M\u00fasica Jazz. Besame mucho. Tico tico no fuba. Moulin rouge [2QxzWdMjI4A].mp4",
            "path": "/home/alanmatzumiya/Videos/container/o4/videos/Oscar Aleman. The Platinum Collection. M\u00fasica Jazz. Besame mucho. Tico tico no fuba. Moulin rouge [2QxzWdMjI4A].mp4",
            "size": 71.211508,
            "url": "https://github.com/circuitalmynds/music_o4/blob/main/videos/Oscar Aleman. The Platinum Collection. M\u00fasica Jazz. Besame mucho. Tico tico no fuba. Moulin rouge [2QxzWdMjI4A].mp4?raw=true"
        },
        {
            "id": "styWiujxWzw",
            "name": "Fru\u0308hbeck dirige Suite espan\u0303ola de Albe\u0301niz [styWiujxWzw].mp4",
            "path": "/home/alanmatzumiya/Videos/container/o4/videos/Fru\u0308hbeck dirige Suite espan\u0303ola de Albe\u0301niz [styWiujxWzw].mp4",
            "size": 94.304088,
            "url": "https://github.com/circuitalmynds/music_o4/blob/main/videos/Fru\u0308hbeck dirige Suite espan\u0303ola de Albe\u0301niz [styWiujxWzw].mp4?raw=true"
        },
        {
            "id": "ZC-q5ye9Wmk",
            "name": "Philipp Fahrbach Jr. - Unsere Frauen, Walzer Op.337 [ZC-q5ye9Wmk].mp4",
            "path": "/home/alanmatzumiya/Videos/container/o4/videos/Philipp Fahrbach Jr. - Unsere Frauen, Walzer Op.337 [ZC-q5ye9Wmk].mp4",
            "size": 50.341021,
            "url": "https://github.com/circuitalmynds/music_o4/blob/main/videos/Philipp Fahrbach Jr. - Unsere Frauen, Walzer Op.337 [ZC-q5ye9Wmk].mp4?raw=true"
        },
        {
            "id": "ZfcHlr3KqyA",
            "name": "Embraceable You [ZfcHlr3KqyA].mp4",
            "path": "/home/alanmatzumiya/Videos/container/o4/videos/Embraceable You [ZfcHlr3KqyA].mp4",
            "size": 16.816663,
            "url": "https://github.com/circuitalmynds/music_o4/blob/main/videos/Embraceable You [ZfcHlr3KqyA].mp4?raw=true"
        },
        {
            "id": "OGQR3Chf9hE",
            "name": "Stelvio Cipriani - Mary's Theme (1969) [OGQR3Chf9hE].mp4",
            "path": "/home/alanmatzumiya/Videos/container/o4/videos/Stelvio Cipriani - Mary's Theme (1969) [OGQR3Chf9hE].mp4",
            "size": 3.310643,
            "url": "https://github.com/circuitalmynds/music_o4/blob/main/videos/Stelvio Cipriani - Mary's Theme (1969) [OGQR3Chf9hE].mp4?raw=true"
        },
        {
            "id": "Nom1vSDZVHM",
            "name": "Chase - Inseguimento (From \uff02The Good, the Bad and the Ugly\uff02) [Nom1vSDZVHM].mp4",
            "path": "/home/alanmatzumiya/Videos/container/o4/videos/Chase - Inseguimento (From \uff02The Good, the Bad and the Ugly\uff02) [Nom1vSDZVHM].mp4",
            "size": 4.992999,
            "url": "https://github.com/circuitalmynds/music_o4/blob/main/videos/Chase - Inseguimento (From \uff02The Good, the Bad and the Ugly\uff02) [Nom1vSDZVHM].mp4?raw=true"
        },
        {
            "id": "IKUkKUIdnHk",
            "name": "Menos Tu Vientre [IKUkKUIdnHk].mp4",
            "path": "/home/alanmatzumiya/Videos/container/o4/videos/Menos Tu Vientre [IKUkKUIdnHk].mp4",
            "size": 6.4755899999999995,
            "url": "https://github.com/circuitalmynds/music_o4/blob/main/videos/Menos Tu Vientre [IKUkKUIdnHk].mp4?raw=true"
        },
        {
            "id": "Um8lgKkWReo",
            "name": "Mozart\uff1a Le nozze di Figaro, K. 492, Act I - No. 7, Trio. Cosa sento! tosto andate [Um8lgKkWReo].mp4",
            "path": "/home/alanmatzumiya/Videos/container/o4/videos/Mozart\uff1a Le nozze di Figaro, K. 492, Act I - No. 7, Trio. Cosa sento! tosto andate [Um8lgKkWReo].mp4",
            "size": 14.246604999999999,
            "url": "https://github.com/circuitalmynds/music_o4/blob/main/videos/Mozart\uff1a Le nozze di Figaro, K. 492, Act I - No. 7, Trio. Cosa sento! tosto andate [Um8lgKkWReo].mp4?raw=true"
        },
        {
            "id": "ibmL5z4gFY0",
            "name": "Pariser Opernball-T\u00e4nze, Op. 147 (Version for Orchestra) [ibmL5z4gFY0].mp4",
            "path": "/home/alanmatzumiya/Videos/container/o4/videos/Pariser Opernball-T\u00e4nze, Op. 147 (Version for Orchestra) [ibmL5z4gFY0].mp4",
            "size": 20.19053,
            "url": "https://github.com/circuitalmynds/music_o4/blob/main/videos/Pariser Opernball-T\u00e4nze, Op. 147 (Version for Orchestra) [ibmL5z4gFY0].mp4?raw=true"
        },
        {
            "id": "KInLwx_fNOc",
            "name": "Mozart\uff1a Le nozze di Figaro, K. 492, Appendix - Al desio di chi t'adora, K. 577 (Replacement... [KInLwx_fNOc].mp4",
            "path": "/home/alanmatzumiya/Videos/container/o4/videos/Mozart\uff1a Le nozze di Figaro, K. 492, Appendix - Al desio di chi t'adora, K. 577 (Replacement... [KInLwx_fNOc].mp4",
            "size": 18.051361999999997,
            "url": "https://github.com/circuitalmynds/music_o4/blob/main/videos/Mozart\uff1a Le nozze di Figaro, K. 492, Appendix - Al desio di chi t'adora, K. 577 (Replacement... [KInLwx_fNOc].mp4?raw=true"
        },
        {
            "id": "eyioFWuNPXg",
            "name": "Fantasie \u00fcber Themen aus 'Der Freisch\u00fctz', S. 451 (After Carl Maria von Weber) [eyioFWuNPXg].mp4",
            "path": "/home/alanmatzumiya/Videos/container/o4/videos/Fantasie \u00fcber Themen aus 'Der Freisch\u00fctz', S. 451 (After Carl Maria von Weber) [eyioFWuNPXg].mp4",
            "size": 15.258835999999999,
            "url": "https://github.com/circuitalmynds/music_o4/blob/main/videos/Fantasie \u00fcber Themen aus 'Der Freisch\u00fctz', S. 451 (After Carl Maria von Weber) [eyioFWuNPXg].mp4?raw=true"
        },
        {
            "id": "69aJ0tRCYaw",
            "name": "Romanza de Inocente [69aJ0tRCYaw].mp4",
            "path": "/home/alanmatzumiya/Videos/container/o4/videos/Romanza de Inocente [69aJ0tRCYaw].mp4",
            "size": 6.339128,
            "url": "https://github.com/circuitalmynds/music_o4/blob/main/videos/Romanza de Inocente [69aJ0tRCYaw].mp4?raw=true"
        },
        {
            "id": "wvfZWAZ2RhY",
            "name": "R\u00edo de los P\u00e1jaros [wvfZWAZ2RhY].mp4",
            "path": "/home/alanmatzumiya/Videos/container/o4/videos/R\u00edo de los P\u00e1jaros [wvfZWAZ2RhY].mp4",
            "size": 7.243821,
            "url": "https://github.com/circuitalmynds/music_o4/blob/main/videos/R\u00edo de los P\u00e1jaros [wvfZWAZ2RhY].mp4?raw=true"
        },
        {
            "id": "iEtJRnmoD0w",
            "name": "Liszt\uff1a Le Vieux Vagabond S.304 [iEtJRnmoD0w].mp4",
            "path": "/home/alanmatzumiya/Videos/container/o4/videos/Liszt\uff1a Le Vieux Vagabond S.304 [iEtJRnmoD0w].mp4",
            "size": 14.413271,
            "url": "https://github.com/circuitalmynds/music_o4/blob/main/videos/Liszt\uff1a Le Vieux Vagabond S.304 [iEtJRnmoD0w].mp4?raw=true"
        },
        {
            "id": "QHmqrhIbczI",
            "name": "Mozart\uff1a Le nozze di Figaro, K. 492, Act IV - Recit. Tutto \u00e8 disposto [QHmqrhIbczI].mp4",
            "path": "/home/alanmatzumiya/Videos/container/o4/videos/Mozart\uff1a Le nozze di Figaro, K. 492, Act IV - Recit. Tutto \u00e8 disposto [QHmqrhIbczI].mp4",
            "size": 2.30038,
            "url": "https://github.com/circuitalmynds/music_o4/blob/main/videos/Mozart\uff1a Le nozze di Figaro, K. 492, Act IV - Recit. Tutto \u00e8 disposto [QHmqrhIbczI].mp4?raw=true"
        },
        {
            "id": "aYlH1L9Tk60",
            "name": "How Long [aYlH1L9Tk60].mp4",
            "path": "/home/alanmatzumiya/Videos/container/o4/videos/How Long [aYlH1L9Tk60].mp4",
            "size": 6.442405,
            "url": "https://github.com/circuitalmynds/music_o4/blob/main/videos/How Long [aYlH1L9Tk60].mp4?raw=true"
        },
        {
            "id": "_fIaoLFe9zE",
            "name": "Piramo e Tisbe\uff1a Recitative\uff1a Piramo, Ah! dove sei\uff1f (Tisbe, Piramo) [_fIaoLFe9zE].mp4",
            "path": "/home/alanmatzumiya/Videos/container/o4/videos/Piramo e Tisbe\uff1a Recitative\uff1a Piramo, Ah! dove sei\uff1f (Tisbe, Piramo) [_fIaoLFe9zE].mp4",
            "size": 3.187884,
            "url": "https://github.com/circuitalmynds/music_o4/blob/main/videos/Piramo e Tisbe\uff1a Recitative\uff1a Piramo, Ah! dove sei\uff1f (Tisbe, Piramo) [_fIaoLFe9zE].mp4?raw=true"
        },
        {
            "id": "l8KEU79785w",
            "name": "Niccol\u00f2 Paganini - El Carnaval de Venecia - Salvatore Accardo [l8KEU79785w].mp4",
            "path": "/home/alanmatzumiya/Videos/container/o4/videos/Niccol\u00f2 Paganini - El Carnaval de Venecia - Salvatore Accardo [l8KEU79785w].mp4",
            "size": 14.462238,
            "url": "https://github.com/circuitalmynds/music_o4/blob/main/videos/Niccol\u00f2 Paganini - El Carnaval de Venecia - Salvatore Accardo [l8KEU79785w].mp4?raw=true"
        },
        {
            "id": "gEIrfX5vMqw",
            "name": "Oh, Lady, Be Good! (Alternative Take 1) [gEIrfX5vMqw].mp4",
            "path": "/home/alanmatzumiya/Videos/container/o4/videos/Oh, Lady, Be Good! (Alternative Take 1) [gEIrfX5vMqw].mp4",
            "size": 14.108357999999999,
            "url": "https://github.com/circuitalmynds/music_o4/blob/main/videos/Oh, Lady, Be Good! (Alternative Take 1) [gEIrfX5vMqw].mp4?raw=true"
        },
        {
            "id": "UnF1RZg9i7A",
            "name": "Liszt - Feuille Morte - \u00c9l\u00e9gie d\u2019apr\u00e8s Mariano Soriano, S.428 (Sergei Yerokhin) [UnF1RZg9i7A].mp4",
            "path": "/home/alanmatzumiya/Videos/container/o4/videos/Liszt - Feuille Morte - \u00c9l\u00e9gie d\u2019apr\u00e8s Mariano Soriano, S.428 (Sergei Yerokhin) [UnF1RZg9i7A].mp4",
            "size": 17.899306,
            "url": "https://github.com/circuitalmynds/music_o4/blob/main/videos/Liszt - Feuille Morte - \u00c9l\u00e9gie d\u2019apr\u00e8s Mariano Soriano, S.428 (Sergei Yerokhin) [UnF1RZg9i7A].mp4?raw=true"
        },
        {
            "id": "abL--9pihnI",
            "name": "L.V.BEETHOVEN\uff1a piano concerto no\u00b01 - Krystian ZIMERMAN;WIENER PHILHARMONIKER [abL--9pihnI].mp4",
            "path": "/home/alanmatzumiya/Videos/container/o4/videos/L.V.BEETHOVEN\uff1a piano concerto no\u00b01 - Krystian ZIMERMAN;WIENER PHILHARMONIKER [abL--9pihnI].mp4",
            "size": 94.39680299999999,
            "url": "https://github.com/circuitalmynds/music_o4/blob/main/videos/L.V.BEETHOVEN\uff1a piano concerto no\u00b01 - Krystian ZIMERMAN;WIENER PHILHARMONIKER [abL--9pihnI].mp4?raw=true"
        },
        {
            "id": "IrcEQ506MY8",
            "name": "Poolside \u2013 Day Mixtape (Official Audio) [IrcEQ506MY8].mp4",
            "path": "/home/alanmatzumiya/Videos/container/o4/videos/Poolside \u2013 Day Mixtape (Official Audio) [IrcEQ506MY8].mp4",
            "size": 83.941114,
            "url": "https://github.com/circuitalmynds/music_o4/blob/main/videos/Poolside \u2013 Day Mixtape (Official Audio) [IrcEQ506MY8].mp4?raw=true"
        },
        {
            "id": "WsUOMwGOlXM",
            "name": "Natty Sat Upon The Rock [WsUOMwGOlXM].mp4",
            "path": "/home/alanmatzumiya/Videos/container/o4/videos/Natty Sat Upon The Rock [WsUOMwGOlXM].mp4",
            "size": 6.969041,
            "url": "https://github.com/circuitalmynds/music_o4/blob/main/videos/Natty Sat Upon The Rock [WsUOMwGOlXM].mp4?raw=true"
        },
        {
            "id": "lTpUJxXPhnI",
            "name": "Liszt - Rondo Fantastique \uff02El Contrabandista\uff02 Valentina Lisitsa [lTpUJxXPhnI].mp4",
            "path": "/home/alanmatzumiya/Videos/container/o4/videos/Liszt - Rondo Fantastique \uff02El Contrabandista\uff02 Valentina Lisitsa [lTpUJxXPhnI].mp4",
            "size": 25.981113999999998,
            "url": "https://github.com/circuitalmynds/music_o4/blob/main/videos/Liszt - Rondo Fantastique \uff02El Contrabandista\uff02 Valentina Lisitsa [lTpUJxXPhnI].mp4?raw=true"
        },
        {
            "id": "e6CbO6xn0C4",
            "name": "Chick Webb = Ella Sings Chick Swings (1939) [Complete LP] [e6CbO6xn0C4].mp4",
            "path": "/home/alanmatzumiya/Videos/container/o4/videos/Chick Webb = Ella Sings Chick Swings (1939) [Complete LP] [e6CbO6xn0C4].mp4",
            "size": 74.59958499999999,
            "url": "https://github.com/circuitalmynds/music_o4/blob/main/videos/Chick Webb = Ella Sings Chick Swings (1939) [Complete LP] [e6CbO6xn0C4].mp4?raw=true"
        },
        {
            "id": "_zpUZ_PoCJM",
            "name": "Etienne Ozi (1754-1813) - Cinqui\u00e8me Concerto pour le basson (1800) [_zpUZ_PoCJM].mp4",
            "path": "/home/alanmatzumiya/Videos/container/o4/videos/Etienne Ozi (1754-1813) - Cinqui\u00e8me Concerto pour le basson (1800) [_zpUZ_PoCJM].mp4",
            "size": 68.247619,
            "url": "https://github.com/circuitalmynds/music_o4/blob/main/videos/Etienne Ozi (1754-1813) - Cinqui\u00e8me Concerto pour le basson (1800) [_zpUZ_PoCJM].mp4?raw=true"
        },
        {
            "id": "IMtx8mizzck",
            "name": "Belgrado - Jeszcze Raz (Videoclip) [IMtx8mizzck].mp4",
            "path": "/home/alanmatzumiya/Videos/container/o4/videos/Belgrado - Jeszcze Raz (Videoclip) [IMtx8mizzck].mp4",
            "size": 12.283643999999999,
            "url": "https://github.com/circuitalmynds/music_o4/blob/main/videos/Belgrado - Jeszcze Raz (Videoclip) [IMtx8mizzck].mp4?raw=true"
        },
        {
            "id": "IAyfq_6CvpY",
            "name": "Run Man Run (Titoli di testa) [IAyfq_6CvpY].mp4",
            "path": "/home/alanmatzumiya/Videos/container/o4/videos/Run Man Run (Titoli di testa) [IAyfq_6CvpY].mp4",
            "size": 9.687683999999999,
            "url": "https://github.com/circuitalmynds/music_o4/blob/main/videos/Run Man Run (Titoli di testa) [IAyfq_6CvpY].mp4?raw=true"
        },
        {
            "id": "vD3il7dPe3c",
            "name": "Piramo e Tisbe\uff1a Aria - Duet\uff1a Pur ti riveggo alfine! (Tisbe, Piramo) [vD3il7dPe3c].mp4",
            "path": "/home/alanmatzumiya/Videos/container/o4/videos/Piramo e Tisbe\uff1a Aria - Duet\uff1a Pur ti riveggo alfine! (Tisbe, Piramo) [vD3il7dPe3c].mp4",
            "size": 5.5265439999999995,
            "url": "https://github.com/circuitalmynds/music_o4/blob/main/videos/Piramo e Tisbe\uff1a Aria - Duet\uff1a Pur ti riveggo alfine! (Tisbe, Piramo) [vD3il7dPe3c].mp4?raw=true"
        },
        {
            "id": "Z42epfm_9Ig",
            "name": "Mighty Sparrow - Only a fool [Z42epfm_9Ig].mp4",
            "path": "/home/alanmatzumiya/Videos/container/o4/videos/Mighty Sparrow - Only a fool [Z42epfm_9Ig].mp4",
            "size": 7.375134,
            "url": "https://github.com/circuitalmynds/music_o4/blob/main/videos/Mighty Sparrow - Only a fool [Z42epfm_9Ig].mp4?raw=true"
        },
        {
            "id": "nRwWeSCTCUg",
            "name": "Rumba-Rhapsody (Arr. M. Bartos and T. Tirino for voices, chorus and orchestra) [nRwWeSCTCUg].mp4",
            "path": "/home/alanmatzumiya/Videos/container/o4/videos/Rumba-Rhapsody (Arr. M. Bartos and T. Tirino for voices, chorus and orchestra) [nRwWeSCTCUg].mp4",
            "size": 12.501429,
            "url": "https://github.com/circuitalmynds/music_o4/blob/main/videos/Rumba-Rhapsody (Arr. M. Bartos and T. Tirino for voices, chorus and orchestra) [nRwWeSCTCUg].mp4?raw=true"
        }
    ],
    "total_size": 939.722677
}